ANCOVA/Ancova_analysis.py
ANCOVA/__init__.py
ANCOVA-0.1.1.dist-info/METADATA
ANCOVA-0.1.1.dist-info/WHEEL
ANCOVA-0.1.1.dist-info/top_level.txt
ANCOVA-0.1.1.dist-info/RECORD
