Metadata-Version: 2.1
Name: ANCOVA
Version: 0.1.1
Summary: Package for ANCOVA analysis and visualization.
Home-page: https://github.com/GERMAN00VP/ANCOVA
Author: Germán Vallejo Palma
Author-email: vallejopalma.g@gmail.com
Classifier: Programming Language :: Python :: 3
Classifier: License :: OSI Approved :: MIT License
Classifier: Operating System :: OS Independent
Requires-Python: >=3.6
Requires-Dist: numpy
Requires-Dist: pandas
Requires-Dist: statsmodels
Requires-Dist: scipy
Requires-Dist: matplotlib
Requires-Dist: seaborn
Requires-Dist: scikit_posthocs
